conditional_kde/__init__.py
conditional_kde/gaussian.py
conditional_kde/interpolated.py
conditional_kde/util.py
conditional_kde-0.1.2.dist-info/licenses/AUTHORS.rst
conditional_kde-0.1.2.dist-info/licenses/LICENSE
conditional_kde-0.1.2.dist-info/METADATA
conditional_kde-0.1.2.dist-info/WHEEL
conditional_kde-0.1.2.dist-info/top_level.txt
conditional_kde-0.1.2.dist-info/RECORD
