Metadata-Version: 2.4
Name: conditional_kde
Version: 0.1.2
Summary: Conditional Kernel Density Estimation.
Author-email: David Prelogović <david.prelogovic@gmail.com>
Maintainer-email: David Prelogović <david.prelogovic@gmail.com>
License: MIT
Project-URL: Homepage, https://github.com/dprelogo/conditional_kde
Project-URL: Repository, https://github.com/dprelogo/conditional_kde
Project-URL: Documentation, https://conditional-kde.readthedocs.io
Keywords: conditional_kde,kernel density estimation,machine learning
Classifier: Development Status :: 2 - Pre-Alpha
Classifier: Intended Audience :: Developers
Classifier: License :: OSI Approved :: MIT License
Classifier: Natural Language :: English
Classifier: Programming Language :: Python :: 3
Classifier: Programming Language :: Python :: 3.9
Classifier: Programming Language :: Python :: 3.10
Classifier: Programming Language :: Python :: 3.11
Classifier: Programming Language :: Python :: 3.12
Requires-Python: >=3.9
License-File: LICENSE
License-File: AUTHORS.rst
Requires-Dist: numpy
Requires-Dist: scipy
Requires-Dist: scikit-learn
Provides-Extra: test
Requires-Dist: pytest>=3; extra == "test"
Provides-Extra: dev
Requires-Dist: pytest>=3; extra == "dev"
Requires-Dist: bump2version; extra == "dev"
Requires-Dist: wheel; extra == "dev"
Requires-Dist: watchdog; extra == "dev"
Requires-Dist: flake8; extra == "dev"
Requires-Dist: tox; extra == "dev"
Requires-Dist: coverage; extra == "dev"
Requires-Dist: Sphinx; extra == "dev"
Requires-Dist: twine; extra == "dev"
Requires-Dist: black; extra == "dev"
Requires-Dist: matplotlib; extra == "dev"
Dynamic: license-file
